gites/__init__.py
gites/cli.py
gites/subpackage/__init__.py
gites/subpackage/_subprocess_handler.py
gites/subpackage/_timing.py
gites/subpackage/config_json_handler.py
gites/subpackage/creat_repo_manager.py
gites/subpackage/datastore_json_handler.py
gites/subpackage/git_push_manager.py
gites/subpackage/package_setup.json
gites/subpackage/pull_manager.py
gites/subpackage/repo_cloner.py
gites/subpackage/util.py
gites/tests/__init__.py
gites/tests/test_datastore_json_handler.py
gites-0.4.7.dist-info/LICENSE
gites-0.4.7.dist-info/METADATA
gites-0.4.7.dist-info/WHEEL
gites-0.4.7.dist-info/entry_points.txt
gites-0.4.7.dist-info/top_level.txt
gites-0.4.7.dist-info/RECORD
