Metadata-Version: 2.1
Name: gites
Version: 0.4.7
Summary: gites is the home of all developers. It provides bulk clone, bulk push, bulk pull etc functions. Contact me with my discord ID: pakkin.lau
Home-page: https://github.com/pakkinlau/gites
Author: Pak Kin LAU
Author-email: kinlau529@gmail.com
License: UNKNOWN
Platform: UNKNOWN
Classifier: Development Status :: 3 - Alpha
Classifier: Intended Audience :: Developers
Classifier: License :: OSI Approved :: MIT License
Classifier: Programming Language :: Python :: 3
Classifier: Programming Language :: Python :: 3.8
